cliquet_fxa/__init__.py
cliquet_fxa/authentication.py
cliquet_fxa/utils.py
cliquet_fxa/tests/__init__.py
cliquet_fxa/tests/test_authentication.py
cliquet_fxa/tests/test_includeme.py
cliquet_fxa/tests/test_views.py
cliquet_fxa/views/__init__.py
cliquet_fxa/views/params.py
cliquet_fxa/views/relier.py
cliquet_fxa-1.4.0.dist-info/DESCRIPTION.rst
cliquet_fxa-1.4.0.dist-info/METADATA
cliquet_fxa-1.4.0.dist-info/RECORD
cliquet_fxa-1.4.0.dist-info/WHEEL
cliquet_fxa-1.4.0.dist-info/metadata.json
cliquet_fxa-1.4.0.dist-info/pbr.json
cliquet_fxa-1.4.0.dist-info/top_level.txt
