Metadata-Version: 2.0
Name: cliquet-fxa
Version: 1.4.0
Summary: Firefox Accounts support in Cliquet
Home-page: https://github.com/mozilla-services/cliquet-fxa
Author: Mozilla Services
Author-email: services-dev@mozilla.com
License: Apache License (2.0)
Keywords: web services
Platform: UNKNOWN
Classifier: Programming Language :: Python
Classifier: Programming Language :: Python :: 2.7
Classifier: Programming Language :: Python :: 3.4
Classifier: Programming Language :: Python :: 3.5
Classifier: Topic :: Internet :: WWW/HTTP
Classifier: Topic :: Internet :: WWW/HTTP :: WSGI :: Application
Classifier: License :: OSI Approved :: Apache Software License
Requires-Dist: cliquet (>=2.9)
Requires-Dist: pyfxa (>=0.0.9)
